{
    "saved_data": {
        "bit-360_site": [
            "bit-360_site/raw/66d968594e0ec98c88d37204.mp4"
        ],
        "investseries_shop": [
            "investseries_shop/66d968424e0ec98c88d37203.mp4"
        ],
        "xtradgpt_online": [
            "xtradgpt_online/66d9687c4e0ec98c88d37205.mp4"
        ]
    },
    "source_data": {
        "bit-360_site": [
            "https://ai-usmcollective.click/videos/TotalEnergies_news_FR.mp4"
        ],
        "investseries_shop": [
            "investseries_shop/66d968424e0ec98c88d37203.mp4"
        ],
        "xtradgpt_online": [
            "https://quontic.site/wp-content/uploads/2024/07/449030935_482215324194392_281914555774571171_n.mp4"
        ]
    },
    "message": "Videos saved successfully",
    "success": true,
    "total_video_count": 3,
    "version": "v0.1"
}
// after result from deepfake
{
    "_id": "66d9687c4e0ec98c88d37205",
    "source_url": "https://xtradgpt.online/",
    "upload_status": "completed",
    "s3_key": "xtradgpt_online/raw/66d9687c4e0ec98c88d37205.mp4",
    "created_at": "2024-09-05T13:44:52.802+00:00",
    "contentType": "video/mp4",
    "processing_status": "done",
    "results": [
        {
            "raw_video_path": "<S3 path for video>",
            "clip_path": "<s3 path for clip>",
            "audio_result": {
                "result": "a number value",
                "table_val": [
                    1,
                    2,
                    3,
                    4,
                    5,
                    6
                ],
                "table_idx": [
                    0,
                    1,
                    2,
                    3,
                    4,
                    5
                ]
            },
            "frame_result": {
                "result": "a number value",
                "table_val": [
                    1,
                    2,
                    3,
                    4,
                    5,
                    6
                ],
                "table_idx": [
                    0,
                    1,
                    2,
                    3,
                    4,
                    5
                ],
                "bboxes": [
                    [
                        1,
                        2,
                        4,
                        6
                    ],
                    [
                        1,
                        3,
                        5,
                        7
                    ],
                    [
                        2,
                        5,
                        8,
                        3
                    ],
                    [
                        2,
                        5,
                        8,
                        3
                    ],
                    [
                        2,
                        5,
                        8,
                        3
                    ],
                    [
                        2,
                        5,
                        8,
                        3
                    ],
                ]
            },
            "final_clip_result": "fake/real"
        },
        {
            "raw_video_path": "<S3 path for video>",
            "clip_path": "<s3 path for clip>",
            "audio_result": {
                "result": "a number value",
                "table_val": [
                    1,
                    2,
                    3,
                    4,
                    5,
                    6
                ],
                "table_idx": [
                    0,
                    1,
                    2,
                    3,
                    4,
                    5
                ]
            },
            "frame_result": {
                "result": "a number value",
                "table_val": [
                    1,
                    2,
                    3,
                    4,
                    5,
                    6
                ],
                "table_idx": [
                    0,
                    1,
                    2,
                    3,
                    4,
                    5
                ],
                "bboxes": [
                    [
                        1,
                        2,
                        4,
                        6
                    ],
                    [
                        1,
                        3,
                        5,
                        7
                    ],
                    [
                        2,
                        5,
                        8,
                        3
                    ],
                    [
                        2,
                        5,
                        8,
                        3
                    ],
                    [
                        2,
                        5,
                        8,
                        3
                    ],
                    [
                        2,
                        5,
                        8,
                        3
                    ],
                ]
            },
            "final_clip_result": "fake/real"
        },
    ]
}
// if pending in sqs queue 
{
    "_id": "66d9687c4e0ec98c88d37205",
    "source_url": "https://xtradgpt.online/",
    "upload_status": "completed",
    "s3_key": "xtradgpt_online/raw/66d9687c4e0ec98c88d37205.mp4",
    "created_at": "2024-09-05T13:44:52.802+00:00",
    "contentType": "video/mp4",
    "processing_status": "pending/in-queue",
    "results": []
}

[
    {
        "_id": "672c5cf49d0afb2e3bede34d",
        "name": "yoyoyo",
        "data": "bruh"
    },
    {
        "_id": "672c8e9579a0112daa1551c4",
        "source_url": "https://xtradgpt.online",
        "upload_status": "completed",
        "s3_key": "https:/raw/672c8e9579a0112daa1551c4.mp4",
        "created_at": "2024-11-07 15:25:33.183000",
        "contentType": "video/mp4",
        "file_name": "449030935_482215324194392_281914555774571171_n.mp4",
        "processing_status": "in-queue"
    },
    {
        "_id": "672cbdbe8c10adf46d16ec45",
        "name": "dummy_data",
        "text": "sample data"
    },
    {
        "_id": "672cbe4d8c10adf46d16ec46",
        "name": "updated dummpy data",
        "text": "sample data"
    },
    {
        "_id": "672cc80da78ea8cf52bd3a23",
        "source_url": "https://xtradgpt.online",
        "upload_status": "completed",
        "s3_key": "https:/raw/672cc80da78ea8cf52bd3a23.mp4",
        "created_at": "2024-11-07 19:30:45.379000",
        "contentType": "video/mp4",
        "file_name": "449030935_482215324194392_281914555774571171_n.mp4",
        "processing_status": "pending"
    },
    {
        "_id": "672cc84ca78ea8cf52bd3a24",
        "source_url": "https://xtradgpt.online",
        "upload_status": "completed",
        "s3_key": "https:/raw/672cc84ca78ea8cf52bd3a24.mp4",
        "created_at": "2024-11-07 19:31:48.263000",
        "contentType": "video/mp4",
        "file_name": "449030935_482215324194392_281914555774571171_n.mp4",
        "processing_status": "pending"
    },
    {
        "_id": "672cc87fa78ea8cf52bd3a25",
        "source_url": "https://xtradgpt.online",
        "upload_status": "completed",
        "s3_key": "https:/raw/672cc87fa78ea8cf52bd3a25.mp4",
        "created_at": "2024-11-07 19:32:39.290000",
        "contentType": "video/mp4",
        "file_name": "449030935_482215324194392_281914555774571171_n.mp4",
        "processing_status": "pending"
    },
    {
        "_id": "672ccdd1a79f2772f78775d3",
        "source_url": "https://xtradgpt.online",
        "upload_status": "completed",
        "s3_key": "https:/raw/672ccdd1a79f2772f78775d3.mp4",
        "created_at": "2024-11-07 19:55:21.966000",
        "contentType": "video/mp4",
        "file_name": "449030935_482215324194392_281914555774571171_n.mp4",
        "processing_status": "pending"
    },
    {
        "_id": "672cce23a79f2772f78775d4",
        "source_url": "https://xtradgpt.online",
        "upload_status": "completed",
        "s3_key": "https:/raw/672cce23a79f2772f78775d4.mp4",
        "created_at": "2024-11-07 19:56:43.304000",
        "contentType": "video/mp4",
        "file_name": "449030935_482215324194392_281914555774571171_n.mp4",
        "processing_status": "in-queue"
    },
    {
        "_id": "672ccff772b95a743ad884d7",
        "source_url": "https://xtradgpt.online",
        "upload_status": "completed",
        "s3_key": "https:/raw/672ccff772b95a743ad884d7.mp4",
        "created_at": "2024-11-07 20:04:31.044000",
        "contentType": "video/mp4",
        "file_name": "449030935_482215324194392_281914555774571171_n.mp4",
        "processing_status": "in-queue"
    }
]